jouets/__init__.py
jouets/addition/__init__.py
jouets/addition/__main__.py
jouets/anagrammes/__init__.py
jouets/anagrammes/__main__.py
jouets/anagrammes/clique.py
jouets/anagrammes/shell.py
jouets/aperitif/__init__.py
jouets/aperitif/__main__.py
jouets/aperitif/data/aperitif.txt
jouets/attente/__init__.py
jouets/attente/__main__.py
jouets/attente/graphiques.py
jouets/attente/choix/__init__.py
jouets/attente/choix/default.py
jouets/attente/discipline/__init__.py
jouets/attente/discipline/default.py
jouets/attente/loiproba/__init__.py
jouets/attente/loiproba/default.py
jouets/attente/sortie/__init__.py
jouets/attente/sortie/default.py
jouets/attente/sortie/unicode.py
jouets/azul/__init__.py
jouets/azul/__main__.py
jouets/bataille/__init__.py
jouets/bataille/__main__.py
jouets/bataille/graphiques.py
jouets/bataille/statistiques.py
jouets/cellulaire/__init__.py
jouets/cellulaire/dimension15/__init__.py
jouets/cellulaire/dimension15/__main__.py
jouets/chemin/__init__.py
jouets/chemin/__main__.py
jouets/dobble/__init__.py
jouets/dobble/__main__.py
jouets/dobble/memobble/__init__.py
jouets/dobble/memobble/__main__.py
jouets/dobble/memobble/errors.py
jouets/dobble/memobble/mmath.py
jouets/dobble/memobble/algo/__init__.py
jouets/dobble/memobble/algo/bipartite.py
jouets/dobble/memobble/algo/complet.py
jouets/dobble/output/__init__.py
jouets/dobble/output/raw.py
jouets/dobble/output/latex/__init__.py
jouets/dobble/output/latex/data/templates/output.tex
jouets/egyptienne/__init__.py
jouets/egyptienne/__main__.py
jouets/erathostene/__init__.py
jouets/erathostene/__main__.py
jouets/euler/__main__.py
jouets/euler/chute.py
jouets/euler/proiepredateur.py
jouets/euler/ressort.py
jouets/euler/satellite.py
jouets/fractale/__init__.py
jouets/fractale/__main__.py
jouets/fractale/options.py
jouets/horloge/__init__.py
jouets/horloge/introuvable/__init__.py
jouets/horloge/introuvable/__main__.py
jouets/labyrinthe/__init__.py
jouets/labyrinthe/__main__.py
jouets-0.6.0.dist-info/AUTHORS
jouets-0.6.0.dist-info/LICENSE
jouets-0.6.0.dist-info/METADATA
jouets-0.6.0.dist-info/WHEEL
jouets-0.6.0.dist-info/entry_points.txt
jouets-0.6.0.dist-info/top_level.txt
jouets-0.6.0.dist-info/zip-safe
jouets-0.6.0.dist-info/RECORD
