Metadata-Version: 2.1
Name: jouets
Version: 0.6.0
Summary: Bric-à-brac de programmes mathématiques « amusants »
Home-page: https://framagit.org/spalax/jouets
Author: Louis Paternault
Author-email: spalax@gresille.org
License: GPLv3 or any later version
Project-URL: Documentation, http://jouets.ababsurdo.fr
Project-URL: Source, https://framagit.org/spalax/jouets
Project-URL: Tracker, https://framagit.org/spalax/jouets/issues
Keywords: games math computer science
Classifier: Development Status :: 5 - Production/Stable
Classifier: Programming Language :: Python
Classifier: Programming Language :: Python :: 3
Classifier: Programming Language :: Python :: 3.11
Classifier: Programming Language :: Python :: 3.12
Classifier: Programming Language :: Python :: 3.13
Classifier: Topic :: Games/Entertainment
Classifier: Intended Audience :: Education
Classifier: License :: OSI Approved :: GNU General Public License v3 or later (GPLv3+)
Classifier: Topic :: Education
Classifier: Topic :: Scientific/Engineering :: Mathematics
Requires-Python: <4,>=3.11
License-File: LICENSE
License-File: AUTHORS
Requires-Dist: argdispatch
Requires-Dist: blessings
Requires-Dist: jinja2
Requires-Dist: matplotlib
Requires-Dist: numpy
Requires-Dist: pillow
Requires-Dist: pygame
Requires-Dist: seaborn
Requires-Dist: termcolor
Requires-Dist: unidecode
